napari_memmap_tiff/__init__.py
napari_memmap_tiff/_version.py
napari_memmap_tiff/_widget.py
napari_memmap_tiff/napari.yaml
napari_memmap_tiff/_tests/__init__.py
napari_memmap_tiff/_tests/test_widget.py
napari_memmap_tiff-1.1.0.dist-info/licenses/LICENSE
napari_memmap_tiff-1.1.0.dist-info/METADATA
napari_memmap_tiff-1.1.0.dist-info/WHEEL
napari_memmap_tiff-1.1.0.dist-info/entry_points.txt
napari_memmap_tiff-1.1.0.dist-info/top_level.txt
napari_memmap_tiff-1.1.0.dist-info/RECORD
