Metadata-Version: 2.4
Name: napari-memmap-tiff
Version: 1.1.0
Summary: When installed and enabled in the options, it adds an option that when enabled will make napari load tiffs via memory mapping instead of fully into RAM.
Author: Matthew Einhorn
Author-email: matt@einhorn.dev
License: 
Project-URL: Bug Tracker, https://github.com/matham/napari-memmap-tiff/issues
Project-URL: Documentation, https://github.com/matham/napari-memmap-tiff#README.md
Project-URL: Source Code, https://github.com/matham/napari-memmap-tiff
Project-URL: User Support, https://github.com/matham/napari-memmap-tiff/issues
Classifier: Development Status :: 2 - Pre-Alpha
Classifier: Framework :: napari
Classifier: Intended Audience :: Developers
Classifier: License :: OSI Approved :: MIT License
Classifier: Operating System :: OS Independent
Classifier: Programming Language :: Python
Classifier: Programming Language :: Python :: 3
Classifier: Programming Language :: Python :: 3 :: Only
Classifier: Programming Language :: Python :: 3.10
Classifier: Programming Language :: Python :: 3.11
Classifier: Programming Language :: Python :: 3.12
Classifier: Programming Language :: Python :: 3.13
Classifier: Topic :: Scientific/Engineering :: Image Processing
Requires-Python: >=3.10
License-File: LICENSE
Requires-Dist: numpy
Requires-Dist: magicgui
Requires-Dist: qtpy
Requires-Dist: scikit-image
Requires-Dist: tifffile
Provides-Extra: testing
Requires-Dist: tox; extra == "testing"
Requires-Dist: pytest; extra == "testing"
Requires-Dist: pytest-cov; extra == "testing"
Requires-Dist: pytest-qt; extra == "testing"
Requires-Dist: napari; extra == "testing"
Requires-Dist: pyqt5; extra == "testing"
Dynamic: license-file
